venorm/__init__.py
venorm/venorm.py
venorm-0.1.0.dist-info/DESCRIPTION.rst
venorm-0.1.0.dist-info/METADATA
venorm-0.1.0.dist-info/RECORD
venorm-0.1.0.dist-info/WHEEL
venorm-0.1.0.dist-info/entry_points.txt
venorm-0.1.0.dist-info/metadata.json
venorm-0.1.0.dist-info/top_level.txt
venorm-0.1.0.dist-info/zip-safe
